{
    "accelerator": {
        "resourceName": "accelerator",
        "service": "elasticInference",
        "resourceArn": "arn:${Partition}:elastic-inference:${Region}:${Account}:elastic-inference-accelerator/${AcceleratorId}",
        "resourceConditions": {},
        "listPrivileges": {},
        "readPrivileges": {},
        "writePrivileges": {
            "Connect": {
                "privilege": "Connect",
                "description": "Grants permission to customer for connecting to Elastic Inference accelerator",
                "accessLevel": "Write",
                "apiDocumentationLink": null,
                "privConditions": {},
                "dependentActions": [],
                "required": true
            }
        },
        "permManPrivileges": {},
        "tagPrivileges": {}
    }
}