{
    "aws:RequestTag/${TagKey}": {
        "condition": "aws:RequestTag/${TagKey}",
        "description": "A key that is present in the request the user makes to the ELB service",
        "type": "String"
    },
    "aws:ResourceTag/${TagKey}": {
        "condition": "aws:ResourceTag/${TagKey}",
        "description": "Global tag key and value pair",
        "type": "String"
    },
    "aws:TagKeys": {
        "condition": "aws:TagKeys",
        "description": "The list of all the tag key names associated with the resource in the request",
        "type": "ArrayOfString"
    },
    "elasticloadbalancing:ResourceTag/": {
        "condition": "elasticloadbalancing:ResourceTag/",
        "description": "The preface string for a tag key and value pair attached to a resource",
        "type": "String"
    },
    "elasticloadbalancing:ResourceTag/${TagKey}": {
        "condition": "elasticloadbalancing:ResourceTag/${TagKey}",
        "description": "A tag key and value pair",
        "type": "String"
    }
}